llama_index/storage/index_store/azure/__init__.py
llama_index/storage/index_store/azure/base.py
llama_index_storage_index_store_azure-0.5.1.dist-info/METADATA
llama_index_storage_index_store_azure-0.5.1.dist-info/WHEEL
llama_index_storage_index_store_azure-0.5.1.dist-info/licenses/LICENSE
llama_index_storage_index_store_azure-0.5.1.dist-info/RECORD
