Metadata-Version: 2.4
Name: llama-index-storage-index-store-azure
Version: 0.5.1
Summary: llama-index index_store azure integration
Author-email: Fran Aguilera <falven2000@hotmail.com>
License-Expression: MIT
License-File: LICENSE
Requires-Python: <4.0,>=3.9
Requires-Dist: llama-index-core<0.15,>=0.13.0
Requires-Dist: llama-index-storage-kvstore-azure<0.5,>=0.4.0
